[
  {
    "orderNo": 3118989,
    "orderNoUrl": "http://www.google.com",
    "date": "Jul 24, 2015",
    "dateStamp": 1437660000000,
    "deliveryDate": "Jan 14, 2014",
    "deliveryDateStamp": 1389618000000,
    "amount": "$1,032.96",
    "status": "created",
    "actions": "http://www.google.com"
  },
  {
    "orderNo": 1415070,
    "orderNoUrl": "http://www.google.com",
    "date": "Nov 21, 2015",
    "dateStamp": 1448024400000,
    "deliveryDate": "May 26, 2014",
    "deliveryDateStamp": 1401026400000,
    "amount": "$3,492.48",
    "status": "cancelled",
    "actions": "http://www.google.com"
  },
  {
    "orderNo": 3184234,
    "orderNoUrl": "http://www.google.com",
    "date": "Mar 10, 2015",
    "dateStamp": 1425906000000,
    "deliveryDate": "Mar 18, 2015",
    "deliveryDateStamp": 1426597200000,
    "amount": "$3,647.94",
    "status": "processing",
    "actions": "http://www.google.com"
  },
  {
    "orderNo": 1697804,
    "orderNoUrl": "http://www.google.com",
    "date": "Jun 16, 2014",
    "dateStamp": 1402840800000,
    "deliveryDate": "May 1, 2015",
    "deliveryDateStamp": 1430402400000,
    "amount": "$3,105.53",
    "status": "created",
    "actions": "http://www.google.com"
  },
  {
    "orderNo": 1268983,
    "orderNoUrl": "http://www.google.com",
    "date": "Jan 16, 2014",
    "dateStamp": 1389790800000,
    "deliveryDate": "May 8, 2015",
    "deliveryDateStamp": 1431007200000,
    "amount": "$1,107.66",
    "status": "processing",
    "actions": "http://www.google.com"
  },
  {
    "orderNo": 1209611,
    "orderNoUrl": "http://www.google.com",
    "date": "Jul 14, 2014",
    "dateStamp": 1405260000000,
    "deliveryDate": "Feb 5, 2014",
    "deliveryDateStamp": 1391518800000,
    "amount": "$1,700.13",
    "status": "dispatched",
    "actions": "http://www.google.com"
  },
  {
    "orderNo": 2490014,
    "orderNoUrl": "http://www.google.com",
    "date": "Jun 25, 2014",
    "dateStamp": 1403618400000,
    "deliveryDate": "Mar 6, 2014",
    "deliveryDateStamp": 1394024400000,
    "amount": "$1,914.48",
    "status": "created",
    "actions": "http://www.google.com"
  },
  {
    "orderNo": 3121199,
    "orderNoUrl": "http://www.google.com",
    "date": "Jun 3, 2014",
    "dateStamp": 1401717600000,
    "deliveryDate": "May 14, 2015",
    "deliveryDateStamp": 1431525600000,
    "amount": "$1,857.44",
    "status": "processing",
    "actions": "http://www.google.com"
  },
  {
    "orderNo": 1534114,
    "orderNoUrl": "http://www.google.com",
    "date": "Apr 8, 2014",
    "dateStamp": 1396879200000,
    "deliveryDate": "Oct 14, 2015",
    "deliveryDateStamp": 1444741200000,
    "amount": "$3,338.44",
    "status": "processing",
    "actions": "http://www.google.com"
  },
  {
    "orderNo": 1197582,
    "orderNoUrl": "http://www.google.com",
    "date": "Apr 1, 2015",
    "dateStamp": 1427806800000,
    "deliveryDate": "May 31, 2015",
    "deliveryDateStamp": 1432994400000,
    "amount": "$3,327.28",
    "status": "created",
    "actions": "http://www.google.com"
  },
  {
    "orderNo": 1496349,
    "orderNoUrl": "http://www.google.com",
    "date": "Feb 27, 2014",
    "dateStamp": 1393419600000,
    "deliveryDate": "Jan 22, 2015",
    "deliveryDateStamp": 1421845200000,
    "amount": "$2,857.22",
    "status": "cancelled",
    "actions": "http://www.google.com"
  },
  {
    "orderNo": 2318868,
    "orderNoUrl": "http://www.google.com",
    "date": "Jul 7, 2015",
    "dateStamp": 1436191200000,
    "deliveryDate": "Aug 23, 2014",
    "deliveryDateStamp": 1408716000000,
    "amount": "$1,901.56",
    "status": "processing",
    "actions": "http://www.google.com"
  },
  {
    "orderNo": 2589131,
    "orderNoUrl": "http://www.google.com",
    "date": "Dec 8, 2014",
    "dateStamp": 1417957200000,
    "deliveryDate": "Mar 25, 2015",
    "deliveryDateStamp": 1427202000000,
    "amount": "$1,194.62",
    "status": "dispatched",
    "actions": "http://www.google.com"
  },
  {
    "orderNo": 1355387,
    "orderNoUrl": "http://www.google.com",
    "date": "Mar 20, 2014",
    "dateStamp": 1395234000000,
    "deliveryDate": "Aug 11, 2014",
    "deliveryDateStamp": 1407679200000,
    "amount": "$3,069.76",
    "status": "created",
    "actions": "http://www.google.com"
  },
  {
    "orderNo": 1233622,
    "orderNoUrl": "http://www.google.com",
    "date": "Feb 21, 2014",
    "dateStamp": 1392901200000,
    "deliveryDate": "Nov 28, 2015",
    "deliveryDateStamp": 1448629200000,
    "amount": "$2,858.44",
    "status": "returned",
    "actions": "http://www.google.com"
  },
  {
    "orderNo": 1756454,
    "orderNoUrl": "http://www.google.com",
    "date": "Feb 4, 2015",
    "dateStamp": 1422968400000,
    "deliveryDate": "Aug 11, 2015",
    "deliveryDateStamp": 1439215200000,
    "amount": "$3,058.50",
    "status": "dispatched",
    "actions": "http://www.google.com"
  },
  {
    "orderNo": 1645170,
    "orderNoUrl": "http://www.google.com",
    "date": "Jun 9, 2015",
    "dateStamp": 1433772000000,
    "deliveryDate": "Aug 8, 2014",
    "deliveryDateStamp": 1407420000000,
    "amount": "$2,012.43",
    "status": "cancelled",
    "actions": "http://www.google.com"
  },
  {
    "orderNo": 1096568,
    "orderNoUrl": "http://www.google.com",
    "date": "Feb 14, 2015",
    "dateStamp": 1423832400000,
    "deliveryDate": "Dec 15, 2014",
    "deliveryDateStamp": 1418562000000,
    "amount": "$1,805.89",
    "status": "processing",
    "actions": "http://www.google.com"
  },
  {
    "orderNo": 2104051,
    "orderNoUrl": "http://www.google.com",
    "date": "Aug 18, 2014",
    "dateStamp": 1408284000000,
    "deliveryDate": "Aug 18, 2015",
    "deliveryDateStamp": 1439820000000,
    "amount": "$2,308.65",
    "status": "cancelled",
    "actions": "http://www.google.com"
  },
  {
    "orderNo": 1306824,
    "orderNoUrl": "http://www.google.com",
    "date": "Apr 22, 2015",
    "dateStamp": 1429624800000,
    "deliveryDate": "Jun 28, 2015",
    "deliveryDateStamp": 1435413600000,
    "amount": "$2,304.48",
    "status": "cancelled",
    "actions": "http://www.google.com"
  },
  {
    "orderNo": 2218347,
    "orderNoUrl": "http://www.google.com",
    "date": "May 27, 2015",
    "dateStamp": 1432648800000,
    "deliveryDate": "Oct 29, 2014",
    "deliveryDateStamp": 1414501200000,
    "amount": "$2,976.57",
    "status": "created",
    "actions": "http://www.google.com"
  },
  {
    "orderNo": 2576748,
    "orderNoUrl": "http://www.google.com",
    "date": "Jan 30, 2015",
    "dateStamp": 1422536400000,
    "deliveryDate": "Aug 26, 2015",
    "deliveryDateStamp": 1440511200000,
    "amount": "$1,953.66",
    "status": "dispatched",
    "actions": "http://www.google.com"
  },
  {
    "orderNo": 2919477,
    "orderNoUrl": "http://www.google.com",
    "date": "Dec 23, 2014",
    "dateStamp": 1419253200000,
    "deliveryDate": "Aug 11, 2015",
    "deliveryDateStamp": 1439215200000,
    "amount": "$2,929.61",
    "status": "cancelled",
    "actions": "http://www.google.com"
  },
  {
    "orderNo": 1090871,
    "orderNoUrl": "http://www.google.com",
    "date": "May 2, 2014",
    "dateStamp": 1398952800000,
    "deliveryDate": "Jul 18, 2014",
    "deliveryDateStamp": 1405605600000,
    "amount": "$3,940.14",
    "status": "processing",
    "actions": "http://www.google.com"
  },
  {
    "orderNo": 2720836,
    "orderNoUrl": "http://www.google.com",
    "date": "Jun 24, 2014",
    "dateStamp": 1403532000000,
    "deliveryDate": "Dec 8, 2014",
    "deliveryDateStamp": 1417957200000,
    "amount": "$2,659.35",
    "status": "returned",
    "actions": "http://www.google.com"
  },
  {
    "orderNo": 2622629,
    "orderNoUrl": "http://www.google.com",
    "date": "Mar 17, 2014",
    "dateStamp": 1394974800000,
    "deliveryDate": "Apr 9, 2015",
    "deliveryDateStamp": 1428501600000,
    "amount": "$3,166.60",
    "status": "returned",
    "actions": "http://www.google.com"
  },
  {
    "orderNo": 2384863,
    "orderNoUrl": "http://www.google.com",
    "date": "Nov 4, 2014",
    "dateStamp": 1415019600000,
    "deliveryDate": "Dec 21, 2014",
    "deliveryDateStamp": 1419080400000,
    "amount": "$1,975.41",
    "status": "processing",
    "actions": "http://www.google.com"
  },
  {
    "orderNo": 2427176,
    "orderNoUrl": "http://www.google.com",
    "date": "Sep 23, 2015",
    "dateStamp": 1442930400000,
    "deliveryDate": "Jul 17, 2014",
    "deliveryDateStamp": 1405519200000,
    "amount": "$1,648.82",
    "status": "processing",
    "actions": "http://www.google.com"
  },
  {
    "orderNo": 3132626,
    "orderNoUrl": "http://www.google.com",
    "date": "Sep 16, 2015",
    "dateStamp": 1442325600000,
    "deliveryDate": "May 22, 2014",
    "deliveryDateStamp": 1400680800000,
    "amount": "$1,547.68",
    "status": "returned",
    "actions": "http://www.google.com"
  },
  {
    "orderNo": 2288182,
    "orderNoUrl": "http://www.google.com",
    "date": "Apr 8, 2014",
    "dateStamp": 1396879200000,
    "deliveryDate": "Feb 28, 2014",
    "deliveryDateStamp": 1393506000000,
    "amount": "$1,212.10",
    "status": "dispatched",
    "actions": "http://www.google.com"
  },
  {
    "orderNo": 2575219,
    "orderNoUrl": "http://www.google.com",
    "date": "Jan 18, 2015",
    "dateStamp": 1421499600000,
    "deliveryDate": "Dec 8, 2014",
    "deliveryDateStamp": 1417957200000,
    "amount": "$2,521.56",
    "status": "returned",
    "actions": "http://www.google.com"
  },
  {
    "orderNo": 3004402,
    "orderNoUrl": "http://www.google.com",
    "date": "Oct 13, 2015",
    "dateStamp": 1444654800000,
    "deliveryDate": "Jan 25, 2015",
    "deliveryDateStamp": 1422104400000,
    "amount": "$3,802.94",
    "status": "dispatched",
    "actions": "http://www.google.com"
  },
  {
    "orderNo": 1099618,
    "orderNoUrl": "http://www.google.com",
    "date": "Mar 22, 2015",
    "dateStamp": 1426942800000,
    "deliveryDate": "Aug 7, 2014",
    "deliveryDateStamp": 1407333600000,
    "amount": "$1,735.57",
    "status": "dispatched",
    "actions": "http://www.google.com"
  },
  {
    "orderNo": 2752701,
    "orderNoUrl": "http://www.google.com",
    "date": "Jan 31, 2015",
    "dateStamp": 1422622800000,
    "deliveryDate": "Apr 28, 2014",
    "deliveryDateStamp": 1398607200000,
    "amount": "$1,132.58",
    "status": "dispatched",
    "actions": "http://www.google.com"
  },
  {
    "orderNo": 2331400,
    "orderNoUrl": "http://www.google.com",
    "date": "Jan 15, 2015",
    "dateStamp": 1421240400000,
    "deliveryDate": "Aug 28, 2015",
    "deliveryDateStamp": 1440684000000,
    "amount": "$2,530.79",
    "status": "created",
    "actions": "http://www.google.com"
  }
]